approveapi_swagger/__init__.py
approveapi_swagger/api_client.py
approveapi_swagger/configuration.py
approveapi_swagger/rest.py
approveapi_swagger/api/__init__.py
approveapi_swagger/api/approve_api.py
approveapi_swagger/models/__init__.py
approveapi_swagger/models/answer_metadata.py
approveapi_swagger/models/create_prompt_request.py
approveapi_swagger/models/error.py
approveapi_swagger/models/prompt.py
approveapi_swagger/models/prompt_answer.py
approveapi_swagger/models/prompt_metadata.py
approveapi_swagger/models/prompt_status.py
test/__init__.py
test/test_answer_metadata.py
test/test_approve_api.py
test/test_create_prompt_request.py
test/test_error.py
test/test_prompt.py
test/test_prompt_answer.py
test/test_prompt_metadata.py
test/test_prompt_status.py
approveapi_swagger-1.0.13.dist-info/METADATA
approveapi_swagger-1.0.13.dist-info/WHEEL
approveapi_swagger-1.0.13.dist-info/top_level.txt
approveapi_swagger-1.0.13.dist-info/RECORD
